<bibliography>
<bibentry abbrev="A."><span>Anguttara Nikāya</span></bibentry>
<bibentry abbrev="Abhms."><span>Abhidhammattha-Saṅgaha</span></bibentry>
<bibentry abbrev="Abhmv."><span>Abhidhammāvatāra</span></bibentry>
<bibentry abbrev="Ap."><span>Apadāna of the Khuddaka Nikāya</span></bibentry>
<bibentry abbrev="As."><span>Atthasālinī = Dhammasaṅgaṇi Aṭṭhakathā</span></bibentry>
<bibentry abbrev="It."><span>Itivuttaka</span></bibentry>
<bibentry abbrev="It.-a."><span>ltivuttaka Aṭṭhakathā = Paramattha-Dīpanī</span></bibentry>
<bibentry abbrev="Ud."><span>Udāna</span></bibentry>
<bibentry abbrev="Ud.-a."><span>Udāna Aṭṭhakathā</span></bibentry>
<bibentry abbrev="C.Pit."><span>Cariyā-piṭaka</span></bibentry>
<bibentry abbrev="Cv."><span>Cūḷavaṁsa</span></bibentry>
<bibentry abbrev="J."><span>Jātaka (Fausböll's ed.)</span></bibentry>
<bibentry abbrev="Th."><span>Thera-gāthā</span></bibentry>
<bibentry abbrev="Thī."><span>Therī-gāthā</span></bibentry>
<bibentry abbrev="D."><span>Dīgha Nikāya</span></bibentry>
<bibentry abbrev="Dh."><span>Dhammapada</span></bibentry>
<bibentry abbrev="Dh.-a."><span>Dhammapada Aṭṭhakathā</span></bibentry>
<bibentry abbrev="Dhs."><span>Dhammasaṅgaṇi</span></bibentry>
<bibentry abbrev="Nd1 (and Nidd. I)"><span>Mahā Niddesa</span></bibentry>
<bibentry abbrev="Netti."><span>Netti-Pakaraṇa</span></bibentry>
<bibentry abbrev="Pts."><span>Paṭisambhidāmagga</span></bibentry>
<bibentry abbrev="Pts.-a."><span>Paṭisambhidā Aṭṭhakathā = Saddhammappakāsinī</span></bibentry>
<bibentry abbrev="Peṭaka."><span>Peṭakopadesa</span></bibentry>
<bibentry abbrev="Pm."><span>Paramatthamñjūsā = Visuddhimagga Aṭṭhakathā = Mahāṭīkā</span></bibentry>
<bibentry abbrev="Ps."><span>Papañcasūdanī = Majjhima Nikāya Aṭṭhakathā</span></bibentry>
<bibentry abbrev="M."><span>Majjhima Nikāya</span></bibentry>
<bibentry abbrev="Mv."><span>(and Mhv.) Mahāvaṁsa</span></bibentry>
<bibentry abbrev="Mil."><span>Milindapañha (V. Trenckner's ed.)</span></bibentry>
<bibentry abbrev="M. Vyut."><span>Mahāvyutpatti</span></bibentry>
<bibentry abbrev="Rūpārūp."><span>Rūpārūpavibhāga</span></bibentry>
<bibentry abbrev="Lal.V."><span>Lalitavistara</span></bibentry>
<bibentry abbrev="Vin."><span>Vinaya</span></bibentry>
<bibentry abbrev="Vis. Mag."><span>Visuddhimagga</span></bibentry>
<bibentry abbrev="Vbh."><span>Vibhanga</span></bibentry>
<bibentry abbrev="Vbh.-a."><span>Vibhanga Aṭṭhakathā = Sammoha-vinodanī</span></bibentry>
<bibentry abbrev="S."><span>Saṁyutta Nikāya</span></bibentry>
<bibentry abbrev="Saddh."><span>Saddhammopāyana</span></bibentry>
<bibentry abbrev="Sn."><span>Sutta-nipāta (Harvard Oriental Series)</span></bibentry>
<bibentry abbrev="Sn.-a."><span>Sutta-nipāta Aṭṭhakathā = Paramatthajotikā</span></bibentry>
<bibentry abbrev="Sp."><span>Samantapāsādikā = Vinaya Aṭṭhakathā</span></bibentry>
<bibentry abbrev="Spk."><span>Sārattha-ppakāsinī = Saṁyutta Nikāya Aṭṭhakathā</span></bibentry>
<bibentry abbrev="Sv."><span>Sumaṅgala-vilāsinī = Dīgha Nikāyạ Aṭṭhakathā</span></bibentry>
</bibliography>
